thermosolver/EOS.py
thermosolver/__init__.py
thermosolver/config_BWRS.py
thermosolver/config_PR_MOD.py
thermosolver/config_RK_MOD.py
thermosolver/config_VDW.py
thermosolver/database.py
thermosolver-0.0.1.dist-info/DESCRIPTION.rst
thermosolver-0.0.1.dist-info/METADATA
thermosolver-0.0.1.dist-info/RECORD
thermosolver-0.0.1.dist-info/WHEEL
thermosolver-0.0.1.dist-info/metadata.json
thermosolver-0.0.1.dist-info/top_level.txt
